entrypoint/__init__.py
entrypoint/init/__init__.py
entrypoint/init/project.py
entrypoint/server/__init__.py
mseep_pywss-0.2.7.dist-info/licenses/LICENSE
pywss/__init__.py
pywss/constant.py
pywss/headers.py
pywss/openapi.py
pywss/routing.py
pywss/testing.py
pywss/utils.py
pywss/websocket.py
pywss/handler/__init__.py
pywss/handler/cache.py
pywss/handler/cors.py
pywss/handler/jwt.py
pywss/handler/recover.py
pywss/handler/static.py
pywss/mcp/__init__.py
mseep_pywss-0.2.7.dist-info/METADATA
mseep_pywss-0.2.7.dist-info/WHEEL
mseep_pywss-0.2.7.dist-info/entry_points.txt
mseep_pywss-0.2.7.dist-info/top_level.txt
mseep_pywss-0.2.7.dist-info/RECORD
